pypitools/__init__.py
pypitools/common.py
pypitools/configs.py
pypitools/git_utils.py
pypitools/main.py
pypitools/name_utils.py
pypitools/process_utils.py
pypitools/static.py
pypitools/utils.py
pypitools-0.0.79.dist-info/LICENSE
pypitools-0.0.79.dist-info/METADATA
pypitools-0.0.79.dist-info/WHEEL
pypitools-0.0.79.dist-info/entry_points.txt
pypitools-0.0.79.dist-info/top_level.txt
pypitools-0.0.79.dist-info/RECORD
