Metadata-Version: 2.1
Name: pypitools
Version: 0.0.79
Summary: pypitools helps you with various pypi tasks
Home-page: https://veltzer.github.io/pypitools
Download-URL: https://github.com/veltzer/pypitools
Author: Mark Veltzer
Author-email: mark.veltzer@gmail.com
Maintainer: Mark Veltzer
Maintainer-email: mark.veltzer@gmail.com
License: MIT
Keywords: pypi,register,upload,erase,delete
Platform: python3
Classifier: Development Status :: 4 - Beta
Classifier: Environment :: Console
Classifier: Operating System :: OS Independent
Classifier: Programming Language :: Python
Classifier: Programming Language :: Python :: 3
Classifier: Programming Language :: Python :: 3 :: Only
Classifier: Programming Language :: Python :: 3.11
Classifier: Topic :: Utilities
Classifier: License :: OSI Approved :: MIT License
License-File: LICENSE
Requires-Dist: pytconf
Requires-Dist: pylogconf
Requires-Dist: twine
Requires-Dist: wheel
Requires-Dist: setuptools
